MANIFEST.in
README.md
setup.py
Flask_Hopak.egg-info/PKG-INFO
Flask_Hopak.egg-info/SOURCES.txt
Flask_Hopak.egg-info/dependency_links.txt
Flask_Hopak.egg-info/not-zip-safe
Flask_Hopak.egg-info/requires.txt
Flask_Hopak.egg-info/top_level.txt
flask_hopak/__init__.py
flask_hopak/actions.py
flask_hopak/base.py
flask_hopak/views.py
flask_hopak/widgets.py
flask_hopak/static/favicon.png
flask_hopak/static/bootstrap/css/bootstrap-responsive.css
flask_hopak/static/bootstrap/css/bootstrap-responsive.min.css
flask_hopak/static/bootstrap/css/bootstrap.css
flask_hopak/static/bootstrap/css/bootstrap.min.css
flask_hopak/static/bootstrap/img/glyphicons-halflings-white.png
flask_hopak/static/bootstrap/img/glyphicons-halflings.png
flask_hopak/static/bootstrap/js/bootstrap.js
flask_hopak/static/bootstrap/js/bootstrap.min.js
flask_hopak/static/chosen/chosen-sprite.png
flask_hopak/static/chosen/chosen.css
flask_hopak/static/chosen/chosen.jquery.min.js
flask_hopak/static/css/style.css
flask_hopak/static/js/jquery-1.8.0.min.js
flask_hopak/static/wysihtml5/bootstrap-wysihtml5-0.0.2.css
flask_hopak/static/wysihtml5/bootstrap-wysihtml5-0.0.2.min.js
flask_hopak/static/wysihtml5/wysihtml5-0.3.0_rc2.min.js
flask_hopak/templates/admin/404.html
flask_hopak/templates/admin/admin_base.html
flask_hopak/templates/admin/aside.html
flask_hopak/templates/admin/base.html
flask_hopak/templates/admin/breadcrambs.html
flask_hopak/templates/admin/counter.html
flask_hopak/templates/admin/footer.html
flask_hopak/templates/admin/header.html
flask_hopak/templates/admin/index.html
flask_hopak/templates/admin/form/add.html
flask_hopak/templates/admin/form/edit.html
flask_hopak/templates/admin/form/list.html
flask_hopak/templates/admin/form/root_view.html
flask_hopak/templates/admin/form/view.html
flask_hopak/templates/admin/include/custom_form.html
flask_hopak/templates/admin/include/js_upload.html
flask_hopak/templates/admin/include/listpage.html
flask_hopak/templates/widgets/wysiwyg.html
tests/__init__.py