Metadata-Version: 1.1
Name: Flask-Hopak
Version: 0.1.0
Summary: Admin interface for Flask that uses Hopak models
Home-page: https://github.com/xen/flask-hopak
Author: Mikhail Kashkin (@xen), Ilya Petrov (@muromec)
Author-email: UNKNOWN
License: BSD
Platform: any
Classifier: Development Status :: 3 - Alpha
Classifier: Environment :: Web Environment
Classifier: Intended Audience :: Developers
Classifier: License :: OSI Approved :: BSD License
Classifier: Operating System :: OS Independent
Classifier: Programming Language :: Python
Classifier: Topic :: Software Development :: Libraries :: Python Modules
